crdlog/__init__.py
crdlog/dlog.py
crdlog-1.0.1.dist-info/METADATA
crdlog-1.0.1.dist-info/WHEEL
crdlog-1.0.1.dist-info/top_level.txt
crdlog-1.0.1.dist-info/RECORD
