Metadata-Version: 2.1
Name: crdlog
Version: 1.0.1
Summary: customed logging for simple scientific computing
Requires-Dist: datetime
Requires-Dist: colorlog
